pytest_aioresponses.py
pytest_aioresponses-0.2.0.dist-info/entry_points.txt
pytest_aioresponses-0.2.0.dist-info/LICENSE
pytest_aioresponses-0.2.0.dist-info/WHEEL
pytest_aioresponses-0.2.0.dist-info/METADATA
pytest_aioresponses-0.2.0.dist-info/RECORD
