Metadata-Version: 2.1
Name: pytest-aioresponses
Version: 0.2.0
Summary: py.test integration for aioresponses
Home-page: https://github.com/pheanex/pytest-aioresponses
License: MIT
Keywords: pytest,aioresponses
Author: Konstantin Manna
Author-email: Konstantin@Manna.uno
Requires-Python: >=3.6,<4.0
Classifier: Development Status :: 4 - Beta
Classifier: Framework :: Pytest
Classifier: Intended Audience :: Developers
Classifier: License :: OSI Approved :: MIT License
Classifier: Operating System :: OS Independent
Classifier: Programming Language :: Python
Classifier: Programming Language :: Python :: 3
Classifier: Programming Language :: Python :: 3 :: Only
Classifier: Programming Language :: Python :: 3.5
Classifier: Programming Language :: Python :: 3.6
Classifier: Programming Language :: Python :: 3.7
Classifier: Programming Language :: Python :: 3.8
Classifier: Programming Language :: Python :: 3.9
Classifier: Programming Language :: Python :: Implementation :: CPython
Classifier: Programming Language :: Python :: Implementation :: PyPy
Classifier: Topic :: Software Development :: Testing
Requires-Dist: aioresponses (>=0.7.1,<0.8.0)
Requires-Dist: pytest (>=3.5.0)
Requires-Dist: pytest-asyncio (>=0.14.0)
Project-URL: Repository, https://github.com/pheanex/pytest-aioresponses
